
<root available-locales="sv_SE" default-locale="sv_SE">
	<dynamic-element dataType="link-to-page" fieldNamespace="ddm" indexType="keyword" name="links" readOnly="false" repeatable="true" required="false" showLabel="true" type="ddm-link-to-page" width="large">
		<dynamic-element dataType="string" indexType="keyword" name="externalUrl" readOnly="false" repeatable="false" required="false" showLabel="true" type="text" width="large">
			<meta-data locale="sv_SE">
				<entry name="label">
					<![CDATA[Eller skriv in en URL]]>
				</entry>
				<entry name="predefinedValue">
					<![CDATA[]]>
				</entry>
				<entry name="tip">
					<![CDATA[]]>
				</entry>
			</meta-data>
		</dynamic-element>
		<dynamic-element dataType="string" indexType="keyword" name="linkText" readOnly="false" repeatable="false" required="false" showLabel="true" type="text" width="large">
			<meta-data locale="sv_SE">
				<entry name="label">
					<![CDATA[Länktext]]>
				</entry>
				<entry name="predefinedValue">
					<![CDATA[]]>
				</entry>
				<entry name="tip">
					<![CDATA[]]>
				</entry>
			</meta-data>
		</dynamic-element>
		<dynamic-element dataType="string" indexType="keyword" multiple="false" name="linkTarget" readOnly="false" repeatable="false" required="false" showLabel="true" type="select" width="">
			<dynamic-element name="option5131" type="option" value="">
				<meta-data locale="sv_SE">
					<entry name="label">
						<![CDATA[I samma fönster]]>
					</entry>
				</meta-data>
			</dynamic-element>
			<dynamic-element name="option5132" type="option" value="_BLANK">
				<meta-data locale="sv_SE">
					<entry name="label">
						<![CDATA[I nytt fönster]]>
					</entry>
				</meta-data>
			</dynamic-element>
			<meta-data locale="sv_SE">
				<entry name="label">
					<![CDATA[Öppna länk]]>
				</entry>
				<entry name="predefinedValue">
					<![CDATA[[""]]]>
				</entry>
				<entry name="tip">
					<![CDATA[]]>
				</entry>
			</meta-data>
		</dynamic-element>
		<dynamic-element dataType="string" indexType="keyword" multiple="false" name="showWhen" readOnly="false" repeatable="false" required="false" showLabel="true" type="select" width="">
			<dynamic-element name="option5817" type="option" value="all">
				<meta-data locale="sv_SE">
					<entry name="label">
						<![CDATA[Alla]]>
					</entry>
				</meta-data>
			</dynamic-element>
			<dynamic-element name="option5818" type="option" value="signed-in">
				<meta-data locale="sv_SE">
					<entry name="label">
						<![CDATA[Inloggade]]>
					</entry>
				</meta-data>
			</dynamic-element>
			<dynamic-element name="option5819" type="option" value="signed-out">
				<meta-data locale="sv_SE">
					<entry name="label">
						<![CDATA[Utloggade]]>
					</entry>
				</meta-data>
			</dynamic-element>
			<meta-data locale="sv_SE">
				<entry name="label">
					<![CDATA[Visa för]]>
				</entry>
				<entry name="predefinedValue">
					<![CDATA[[""]]]>
				</entry>
				<entry name="tip">
					<![CDATA[]]>
				</entry>
			</meta-data>
		</dynamic-element>
		<dynamic-element dataType="string" indexType="keyword" name="cssClass" readOnly="false" repeatable="false" required="false" showLabel="true" type="text" width="large">
			<meta-data locale="sv_SE">
				<entry name="label">
					<![CDATA[CSS-klass]]>
				</entry>
				<entry name="predefinedValue">
					<![CDATA[]]>
				</entry>
				<entry name="tip">
					<![CDATA[]]>
				</entry>
			</meta-data>
		</dynamic-element>
		<meta-data locale="sv_SE">
			<entry name="label">
				<![CDATA[Link to Page]]>
			</entry>
			<entry name="predefinedValue">
				<![CDATA[]]>
			</entry>
			<entry name="tip">
				<![CDATA[]]>
			</entry>
		</meta-data>
	</dynamic-element>
</root>